[
  {
    "name": "quarto-utils",
    "organization": "U.S. Geological Survey",
    "description": "utilities for references in quarto",
    "version": "main",
    "status": "Development",

    "permissions": {
      "usageType": "openSource",
      "licenses": [
        {
          "name": "Public Domain, CC0-1.0",
          "URL": "https://raw.githubusercontent.com/DOI-USGS/quarto-utils/main/LICENSE.md"
        }
      ]
    },

    "homepageURL": "https://github.com/DOI-USGS/quarto-utils",
    "downloadURL": "https://github.com/DOI-USGS/quarto-utils/archive/refs/heads/main.zip",
    "disclaimerURL": "https://raw.githubusercontent.com/DOI-USGS/quarto-utils/main/DISCLAIMER.md",
    "repositoryURL": "https://github.com/DOI-USGS/quarto-utils.git",
    "vcs": "git",

    "laborHours": 33.5,

    "tags": [
      "quarto",
      "python",
      "bibtex"

    ],

    "languages": [
      "python"
    ],

    "contact": {
      "name": "Michael Fienen",
      "email": "mnfienen@usgs.gov"
    },

    "date": {
      "metadataLastUpdated": "2024-02-28"
    }
  },

    {
    "name": "quarto-utils",
    "organization": "U.S. Geological Survey",
    "description": "utilities for references in quarto",
    "version": "1.0",
    "status": "Production",

    "permissions": {
      "usageType": "openSource",
      "licenses": [
        {
          "name": "Public Domain, CC0-1.0",
          "URL": "https://raw.githubusercontent.com/DOI-USGS/quarto-utils/v1.0/LICENSE.md"
        }
      ]
    },

    "homepageURL": "https://github.com/DOI-USGS/quarto-utils",
    "downloadURL": "https://github.com/DOI-USGS/quarto-utils/archive/refs/heads/v1.0.zip",
    "disclaimerURL": "https://raw.githubusercontent.com/DOI-USGS/quarto-utils/v1.0/DISCLAIMER.md",
    "repositoryURL": "https://github.com/DOI-USGS/quarto-utils.git",

    "laborHours": 34.75,

    "tags": [
      "quarto",
      "python",
      "bibtex"

    ],

    "languages": [
      "python"
    ],

    "contact": {
      "name": "Michael Fienen",
      "email": "mnfienen@usgs.gov"
    },

    "date": {
      "metadataLastUpdated": "2024-02-28"
    }
  }
]
